{
    "Component|None": {
        "fontsize": 8,
        "fontbold": 1,
        "bordercolor": "EDD5CB",
        "backgroundcolor": "F9EAEA",
        "shape": "shape=module;",
        "arrow": null,
        "fill": null,
        "dashed": null,
        "linecolor": null
    },
    "Package|None": {
        "fontsize": 8,
        "fontbold": 1,
        "bordercolor": "EDD5CB",
        "backgroundcolor": "FAF3F0",
        "shape": "shape=folder;",
        "arrow": null,
        "fill": null,
        "dashed": null,
        "linecolor": null
    },
    "Actor|None": {
        "fontsize": 8,
        "fontbold": 1,
        "bordercolor": "EDD5CB",
        "backgroundcolor": "F4EFDA",
        "shape": "shape=umlActor;",
        "arrow": null,
        "fill": null,
        "dashed": null,
        "linecolor": null
    },
    "ExecutionEnvironment|None": {
        "fontsize": 8,
        "fontbold": 1,
        "bordercolor": "EDD5CB",
        "backgroundcolor": "DAEAFC",
        "shape": "shape=cube;size=5;direction=south;",
        "arrow": null,
        "fill": null,
        "dashed": null,
        "linecolor": null
    },
    "Node|None": {
        "fontsize": 8,
        "fontbold": 1,
        "bordercolor": "EDD5CB",
        "backgroundcolor": "CDE5F5",
        "shape": "shape=cube;size=5;direction=south;",
        "arrow": null,
        "fill": null,
        "dashed": null,
        "linecolor": null
    },
    "Event|None": {
        "fontsize": 8,
        "fontbold": 1,
        "bordercolor": "EDD5CB",
        "backgroundcolor": "FCC5C2",
        "shape": "ellipse;",
        "arrow": null,
        "fill": null,
        "dashed": null,
        "linecolor": null
    },
    "StartEvent|None": {
        "fontsize": 8,
        "fontbold": 1,
        "bordercolor": "EDD5CB",
        "backgroundcolor": "FCC5C2",
        "shape": "ellipse;",
        "arrow": null,
        "fill": null,
        "dashed": null,
        "linecolor": null
    },
    "EndEvent|None": {
        "fontsize": 8,
        "fontbold": 1,
        "bordercolor": "EDD5CB",
        "backgroundcolor": "FCC5C2",
        "shape": "ellipse;",
        "arrow": null,
        "fill": null,
        "dashed": null,
        "linecolor": null
    },
    "StateNode|None": {
        "fontsize": 8,
        "fontbold": 1,
        "bordercolor": "EDD5CB",
        "backgroundcolor": "EDD5CB",
        "shape": "ellipse;",
        "arrow": null,
        "fill": null,
        "dashed": null,
        "linecolor": null
    },
    "Decision|None": {
        "fontsize": 8,
        "fontbold": 1,
        "bordercolor": "EDD5CB",
        "backgroundcolor": "CCE2A0",
        "shape": "rhombus;",
        "arrow": null,
        "fill": null,
        "dashed": null,
        "linecolor": null
    },
    "Gateway|None": {
        "fontsize": 8,
        "fontbold": 1,
        "bordercolor": "EDD5CB",
        "backgroundcolor": "CCE2A0",
        "shape": "rhombus;",
        "arrow": null,
        "fill": null,
        "dashed": null,
        "linecolor": null
    },
    "Activity|None": {
        "fontsize": 8,
        "fontbold": 1,
        "bordercolor": "EDD5CB",
        "backgroundcolor": "FBF9DB",
        "shape": "rounded=1;",
        "arrow": null,
        "fill": null,
        "dashed": null,
        "linecolor": null
    },
    "Class|None": {
        "fontsize": 8,
        "fontbold": 1,
        "bordercolor": "EDD5CB",
        "backgroundcolor": "FDFAF7",
        "shape": null,
        "arrow": null,
        "fill": null,
        "dashed": null,
        "linecolor": null
    },
    "Note|None": {
        "fontsize": 8,
        "fontbold": 0,
        "bordercolor": "658A99",
        "backgroundcolor": "FFFFFF",
        "shape": "shape=note;",
        "arrow": null,
        "fill": null,
        "dashed": null,
        "linecolor": null
    },
    "None|ArchiMate_Application": {
        "fontsize": 8,
        "fontbold": 1,
        "bordercolor": "EDD5CB",
        "backgroundcolor": "C0FFFF",
        "shape": null,
        "arrow": null,
        "fill": null,
        "dashed": null,
        "linecolor": null
    },
    "None|ArchiMate_Business": {
        "fontsize": 8,
        "fontbold": 1,
        "bordercolor": "EDD5CB",
        "backgroundcolor": "FFFFC0",
        "shape": null,
        "arrow": null,
        "fill": null,
        "dashed": null,
        "linecolor": null
    },
    "Node|ArchiMate_Node": {
        "fontsize": 8,
        "fontbold": 1,
        "bordercolor": "EDD5CB",
        "backgroundcolor": "C0FFC0",
        "shape": "shape=cube;size=5;direction=south;",
        "arrow": null,
        "fill": null,
        "dashed": null,
        "linecolor": null
    },
    "Device|ArchiMate_Device": {
        "fontsize": 8,
        "fontbold": 1,
        "bordercolor": "EDD5CB",
        "backgroundcolor": "C0FFC0",
        "shape": "shape=cube;size=5;direction=south;",
        "arrow": null,
        "fill": null,
        "dashed": null,
        "linecolor": null
    },
    "SystemSoftware|ArchiMate_SystemSoftware": {
        "fontsize": 8,
        "fontbold": 1,
        "bordercolor": "EDD5CB",
        "backgroundcolor": "C0FFC0",
        "shape": "shape=cube;size=5;direction=south;",
        "arrow": null,
        "fill": null,
        "dashed": null,
        "linecolor": null
    },
    "Artifact|ArchiMate_Artifact": {
        "fontsize": 8,
        "fontbold": 1,
        "bordercolor": "EDD5CB",
        "backgroundcolor": "C0FFC0",
        "shape": null,
        "arrow": null,
        "fill": null,
        "dashed": null,
        "linecolor": null
    },
    "TechnologyCollaboration|ArchiMate_TechnologyCollaboration": {
        "fontsize": 8,
        "fontbold": 1,
        "bordercolor": "EDD5CB",
        "backgroundcolor": "C0FFC0",
        "shape": null,
        "arrow": null,
        "fill": null,
        "dashed": null,
        "linecolor": null
    },
    "TechnologyInterface|ArchiMate_TechnologyInterface": {
        "fontsize": 8,
        "fontbold": 1,
        "bordercolor": "EDD5CB",
        "backgroundcolor": "C0FFC0",
        "shape": null,
        "arrow": null,
        "fill": null,
        "dashed": null,
        "linecolor": null
    },
    "InformationFlow|None": {
        "fontsize": 8,
        "fontbold": null,
        "bordercolor": null,
        "backgroundcolor": null,
        "shape": null,
        "arrow": "open",
        "fill": 0,
        "dashed": 1,
        "linecolor": "000000"
    },
    "Dependency|None": {
        "fontsize": 8,
        "fontbold": null,
        "bordercolor": null,
        "backgroundcolor": null,
        "shape": null,
        "arrow": "open",
        "fill": 0,
        "dashed": 1,
        "linecolor": "000000"
    },
    "Association|None": {
        "fontsize": 8,
        "fontbold": null,
        "bordercolor": null,
        "backgroundcolor": null,
        "shape": null,
        "arrow": "none",
        "fill": 0,
        "dashed": 0,
        "linecolor": "000000"
    },
    "Realization|None": {
        "fontsize": 8,
        "fontbold": null,
        "bordercolor": null,
        "backgroundcolor": null,
        "shape": null,
        "arrow": "block",
        "fill": 0,
        "dashed": 1,
        "linecolor": "000000"
    },
    "Realisation|None": {
        "fontsize": 8,
        "fontbold": null,
        "bordercolor": null,
        "backgroundcolor": null,
        "shape": null,
        "arrow": "block",
        "fill": 0,
        "dashed": 1,
        "linecolor": "000000"
    },
    "NoteLink|None": {
        "fontsize": 8,
        "fontbold": null,
        "bordercolor": null,
        "backgroundcolor": null,
        "shape": null,
        "arrow": "none",
        "fill": 0,
        "dashed": 1,
        "linecolor": "000000"
    },
    "ControlFlow|None": {
        "fontsize": 8,
        "fontbold": null,
        "bordercolor": null,
        "backgroundcolor": null,
        "shape": null,
        "arrow": "block",
        "fill": 1,
        "dashed": 0,
        "linecolor": "000000"
    }
}